bert_tokenizer/__init__.py
bert_tokenizer/libbert_tokenizer.dll
bert_tokenizer/libbert_tokenizer.dylib
bert_tokenizer/libbert_tokenizer.so
bert_tokenizer/tokenizer.py
bert_tokenizer-0.1.5.dist-info/METADATA
bert_tokenizer-0.1.5.dist-info/RECORD
bert_tokenizer-0.1.5.dist-info/WHEEL
bert_tokenizer-0.1.5.dist-info/top_level.txt
