Metadata-Version: 2.1
Name: bert-tokenizer
Version: 0.1.5
Summary: A Tokenizer for Bert model
Home-page: UNKNOWN
Author: Li Fang
Author-email: golifang1234@gmail.com
License: UNKNOWN
Platform: UNKNOWN
Classifier: Programming Language :: Python :: 3
Classifier: Programming Language :: Python :: 2
Classifier: License :: OSI Approved :: MIT License
Classifier: Operating System :: OS Independent
